dnsupdate.py
dnsupdate-0.4.1.dist-info/licenses/LICENSE.txt
dnsupdate-0.4.1.dist-info/METADATA
dnsupdate-0.4.1.dist-info/WHEEL
dnsupdate-0.4.1.dist-info/entry_points.txt
dnsupdate-0.4.1.dist-info/top_level.txt
dnsupdate-0.4.1.dist-info/RECORD
