Metadata-Version: 2.4
Name: dnsupdate
Version: 0.4.1
Summary: A modern and flexible dynamic DNS client
Author-email: Ben Wolsieffer <benwolsieffer@gmail.com>
License-Expression: GPL-3.0-or-later
Keywords: dns
Classifier: Programming Language :: Python :: 3.5
Classifier: Development Status :: 4 - Beta
Classifier: Intended Audience :: System Administrators
Classifier: Natural Language :: English
Classifier: Topic :: System :: Networking
Requires-Python: >=3.5
License-File: LICENSE.txt
Requires-Dist: PyYAML
Requires-Dist: requests
Provides-Extra: router-address-scraping
Requires-Dist: beautifulsoup4; extra == "router-address-scraping"
Provides-Extra: local-address-provider
Requires-Dist: netifaces; extra == "local-address-provider"
Provides-Extra: build-docs
Requires-Dist: sphinx-argparse; extra == "build-docs"
Dynamic: license-file
